pyssian/__init__.py
pyssian/chemistryutils.py
pyssian/classutils.py
pyssian/gaussianclasses.py
pyssian/linkjobparsers.py
pyssian/tests/__init__.py
pyssian/tests/test_chemistryutils.py
pyssian/tests/test_gaussianinput.py
pyssian/tests/test_linkjobparsers.py
pyssian/tests/test_files/General.txt
pyssian/tests/test_files/General_regex.txt
pyssian/tests/test_files/H_rad.com
pyssian/tests/test_files/l1.txt
pyssian/tests/test_files/l101.txt
pyssian/tests/test_files/l103.txt
pyssian/tests/test_files/l103_convergence.txt
pyssian/tests/test_files/l103_derivatives.txt
pyssian/tests/test_files/l103_parameters.txt
pyssian/tests/test_files/l120.txt
pyssian/tests/test_files/l122.txt
pyssian/tests/test_files/l123.txt
pyssian/tests/test_files/l123_orientation.txt
pyssian/tests/test_files/l1_properties.txt
pyssian/tests/test_files/l1_regex.txt
pyssian/tests/test_files/l202.txt
pyssian/tests/test_files/l202_dmatrices.txt
pyssian/tests/test_files/l202_orientations.txt
pyssian/tests/test_files/l202_regex.txt
pyssian/tests/test_files/l502.txt
pyssian/tests/test_files/l601.txt
pyssian/tests/test_files/l601_regex.txt
pyssian/tests/test_files/l716.txt
pyssian/tests/test_files/l716_reEContrib.txt
pyssian/tests/test_files/l716_reFrequencies.txt
pyssian/tests/test_files/l716_reIRSpectrum.txt
pyssian/tests/test_files/l716_reThermo.txt
pyssian/tests/test_files/l716_redipole.txt
pyssian/tests/test_files/l716_refreqdisplacements.txt
pyssian/tests/test_files/l716_refreqtxt.txt
pyssian/tests/test_files/l804.txt
pyssian/tests/test_files/l804_properties.txt
pyssian/tests/test_files/l913.txt
pyssian/tests/test_files/l913_MP4.txt
pyssian/tests/test_files/l913_ccsdt.txt
pyssian/tests/test_files/l914.txt
pyssian/tests/test_files/l914_properties.txt
pyssian/tests/test_files/tbutyl.com
pyssian-1.1.1.dist-info/licenses/LICENSE
pyssian-1.1.1.dist-info/METADATA
pyssian-1.1.1.dist-info/WHEEL
pyssian-1.1.1.dist-info/top_level.txt
pyssian-1.1.1.dist-info/RECORD
