Metadata-Version: 2.4
Name: pyssian
Version: 1.1.1
Summary: Parser Library for Gaussian Files
Home-page: https://github.com/maserasgroup-repo/pyssian
Author: Raúl Pérez-Soto
Author-email: rperezsoto.research@gmail.com
Project-URL: Bug Reports, https://github.com/maserasgroup-repo/pyssian/issues
Project-URL: Source, https://github.com/maserasgroup-repo/pyssian
Project-URL: Docs, https://maserasgroup-repo.github.io/pyssian/
Keywords: compchem,gaussian,parser
Classifier: License :: OSI Approved :: MIT License
Classifier: Programming Language :: Python :: 3
Classifier: Programming Language :: Python :: 3.6
Classifier: Programming Language :: Python :: 3.7
Classifier: Programming Language :: Python :: 3.8
Classifier: Programming Language :: Python :: 3.9
Classifier: Programming Language :: Python :: 3.10
Requires-Python: >=3.6
License-File: LICENSE
Requires-Dist: setuptools
Requires-Dist: pathlib
Requires-Dist: numpy
Dynamic: author
Dynamic: author-email
Dynamic: classifier
Dynamic: description
Dynamic: description-content-type
Dynamic: home-page
Dynamic: keywords
Dynamic: license-file
Dynamic: project-url
Dynamic: requires-dist
Dynamic: requires-python
Dynamic: summary
